{
  "四川_物理_2025": {
    "province": "四川",
    "subject_type": "物理",
    "year": 2025,
    "source": "四川省教育考试院",
    "title": "2025年普通高校招生考生成绩分段统计表（物理类）",
    "url": "https://gaokao.eol.cn/si_chuan/dongtai/202507/t20250702_2678480.shtml",
    "note": "取官方公布的分数段阈值锚点（含本科线438、特控线518对应位次），分数段之间按对数位次线性插值；高/低分段按趋势外推并在界面标注为估算。数据为公开统计事实，仅供位次换算参考。"
  },
  "四川_历史_2025": {
    "province": "四川",
    "subject_type": "历史",
    "year": 2025,
    "source": "四川省教育考试院",
    "title": "2025年普通高考成绩分段统计表（历史类）",
    "url": "https://gaokao.eol.cn/si_chuan/dongtai/202507/t20250702_2678481.shtml",
    "note": "取官方公布的关键分数段累计人数（位次）锚点，分数段间按对数位次线性插值，高/低分段按趋势外推并标注估算。数据为公开统计事实，仅供位次换算参考。"
  },
  "广东_物理_2025": {
    "province": "广东",
    "subject_type": "物理",
    "year": 2025,
    "source": "广东省教育考试院",
    "title": "2025年普通高考成绩分段统计表（物理类）",
    "url": "https://gaokao.eol.cn/guang_dong/dongtai/202506/t20250625_2676895.shtml",
    "note": "取官方公布的关键分数段累计人数（位次）锚点，分数段间按对数位次线性插值，高/低分段按趋势外推并标注估算。数据为公开统计事实，仅供位次换算参考。"
  },
  "广东_历史_2025": {
    "province": "广东",
    "subject_type": "历史",
    "year": 2025,
    "source": "广东省教育考试院",
    "title": "2025年普通高考成绩分段统计表（历史类）",
    "url": "https://gaokao.eol.cn/guang_dong/dongtai/202506/t20250625_2676895.shtml",
    "note": "取官方公布的关键分数段累计人数（位次）锚点，分数段间按对数位次线性插值，高/低分段按趋势外推并标注估算。数据为公开统计事实，仅供位次换算参考。"
  },
  "河南_物理_2025": {
    "province": "河南",
    "subject_type": "物理",
    "year": 2025,
    "source": "河南省教育考试院",
    "title": "2025年普通高考成绩分段统计表（物理类）",
    "url": "https://gaokao.eol.cn/he_nan/dongtai/202506/t20250625_2676859.shtml",
    "note": "取官方公布的关键分数段累计人数（位次）锚点，分数段间按对数位次线性插值，高/低分段按趋势外推并标注估算。数据为公开统计事实，仅供位次换算参考。"
  },
  "河南_历史_2025": {
    "province": "河南",
    "subject_type": "历史",
    "year": 2025,
    "source": "河南省教育考试院",
    "title": "2025年普通高考成绩分段统计表（历史类）",
    "url": "https://gaokao.eol.cn/he_nan/dongtai/202506/t20250625_2676858.shtml",
    "note": "取官方公布的关键分数段累计人数（位次）锚点，分数段间按对数位次线性插值，高/低分段按趋势外推并标注估算。数据为公开统计事实，仅供位次换算参考。"
  },
  "河北_物理_2025": {
    "province": "河北",
    "subject_type": "物理",
    "year": 2025,
    "source": "河北省教育考试院",
    "title": "2025年普通高考成绩分段统计表（物理类）",
    "url": "https://gaokao.eol.cn/he_bei/dongtai/202506/t20250624_2676695.shtml",
    "note": "取官方公布的关键分数段累计人数（位次）锚点，分数段间按对数位次线性插值，高/低分段按趋势外推并标注估算。数据为公开统计事实，仅供位次换算参考。"
  },
  "河北_历史_2025": {
    "province": "河北",
    "subject_type": "历史",
    "year": 2025,
    "source": "河北省教育考试院",
    "title": "2025年普通高考成绩分段统计表（历史类）",
    "url": "https://gaokao.eol.cn/he_bei/dongtai/202506/t20250624_2676695.shtml",
    "note": "取官方公布的关键分数段累计人数（位次）锚点，分数段间按对数位次线性插值，高/低分段按趋势外推并标注估算。数据为公开统计事实，仅供位次换算参考。"
  },
  "江苏_物理_2025": {
    "province": "江苏",
    "subject_type": "物理",
    "year": 2025,
    "source": "江苏省教育考试院",
    "title": "2025年普通高考成绩分段统计表（物理类）",
    "url": "https://www.zgjssw.gov.cn/yaowen/202506/t20250625_8498558.shtml",
    "note": "取官方公布的关键分数段累计人数（位次）锚点，分数段间按对数位次线性插值，高/低分段按趋势外推并标注估算。数据为公开统计事实，仅供位次换算参考。"
  },
  "江苏_历史_2025": {
    "province": "江苏",
    "subject_type": "历史",
    "year": 2025,
    "source": "江苏省教育考试院",
    "title": "2025年普通高考成绩分段统计表（历史类）",
    "url": "https://www.zgjssw.gov.cn/yaowen/202506/t20250625_8498558.shtml",
    "note": "取官方公布的关键分数段累计人数（位次）锚点，分数段间按对数位次线性插值，高/低分段按趋势外推并标注估算。数据为公开统计事实，仅供位次换算参考。"
  },
  "山东_综合_2025": {
    "province": "山东",
    "subject_type": "综合",
    "year": 2025,
    "source": "山东省教育招生考试院",
    "title": "2025年普通高校招生考生成绩分段统计表（综合）",
    "url": "https://www.sdzk.cn/",
    "note": "完整官方逐分段一分一段表（普通类一段+二段，覆盖约150~750分），由用户购买并提供。换算器直接逐段查表/插值。数据为山东省教育招生考试院公布的成绩分段统计事实。"
  },
  "北京_综合_2025": {
    "province": "北京",
    "subject_type": "综合",
    "year": 2025,
    "source": "北京市教育考试院",
    "title": "2025年普通高考成绩分段统计表（综合）",
    "url": "https://gaokao.eol.cn/bei_jing/dongtai/202506/t20250625_2676934.shtml",
    "note": "3+3 模式省份不分物理/历史，为单张综合一分一段表。取官方公布的关键分数段累计人数（位次）锚点，分段间对数插值、超范围按趋势外推并标注估算。数据为公开统计事实，仅供位次换算参考。"
  },
  "天津_综合_2025": {
    "province": "天津",
    "subject_type": "综合",
    "year": 2025,
    "source": "天津市教育考试院",
    "title": "2025年普通高考成绩分段统计表（综合）",
    "url": "https://news.qq.com/rain/a/20250623A078TW00",
    "note": "3+3 模式省份不分物理/历史，为单张综合一分一段表。取官方公布的关键分数段累计人数（位次）锚点，分段间对数插值、超范围按趋势外推并标注估算。数据为公开统计事实，仅供位次换算参考。"
  },
  "浙江_综合_2025": {
    "province": "浙江",
    "subject_type": "综合",
    "year": 2025,
    "source": "浙江省教育考试院",
    "title": "2025年普通高考成绩分段统计表（综合）",
    "url": "https://gaokao.eol.cn/zhe_jiang/dongtai/202506/t20250625_2677143.shtml",
    "note": "3+3 模式省份不分物理/历史，为单张综合一分一段表。取官方公布的关键分数段累计人数（位次）锚点，分段间对数插值、超范围按趋势外推并标注估算。数据为公开统计事实，仅供位次换算参考。"
  },
  "上海_综合_2025": {
    "province": "上海",
    "subject_type": "综合",
    "year": 2025,
    "source": "上海市教育考试院",
    "title": "2025年普通高考成绩分段统计表（综合（满分660））",
    "url": "https://gaokao.eol.cn/shang_hai/dongtai/202506/t20250623_2676341.shtml",
    "note": "3+3 模式省份不分物理/历史，为单张综合一分一段表。取官方公布的关键分数段累计人数（位次）锚点，分段间对数插值、超范围按趋势外推并标注估算。注意本省满分为660。数据为公开统计事实，仅供位次换算参考。"
  },
  "海南_综合_2025": {
    "province": "海南",
    "subject_type": "综合",
    "year": 2025,
    "source": "海南省教育考试院",
    "title": "2025年普通高考成绩分段统计表（综合（满分900））",
    "url": "https://www.gk100.com/read_41934287.htm",
    "note": "3+3 模式省份不分物理/历史，为单张综合一分一段表。取官方公布的关键分数段累计人数（位次）锚点，分段间对数插值、超范围按趋势外推并标注估算。注意本省满分为900。数据为公开统计事实，仅供位次换算参考。"
  },
  "山东_综合_2022": {
    "province": "山东",
    "subject_type": "综合",
    "year": 2022,
    "source": "山东省教育招生考试院",
    "title": "2022年普通高校招生考生成绩分段统计表（综合）",
    "url": "https://www.sdzk.cn/",
    "note": "完整官方逐分段一分一段表（普通类一段+二段，覆盖约150~750分），由用户购买并提供。换算器直接逐段查表/插值。数据为山东省教育招生考试院公布的成绩分段统计事实。"
  },
  "山东_综合_2023": {
    "province": "山东",
    "subject_type": "综合",
    "year": 2023,
    "source": "山东省教育招生考试院",
    "title": "2023年普通高校招生考生成绩分段统计表（综合）",
    "url": "https://www.sdzk.cn/",
    "note": "完整官方逐分段一分一段表（普通类一段+二段，覆盖约150~750分），由用户购买并提供。换算器直接逐段查表/插值。数据为山东省教育招生考试院公布的成绩分段统计事实。"
  },
  "山东_综合_2024": {
    "province": "山东",
    "subject_type": "综合",
    "year": 2024,
    "source": "山东省教育招生考试院",
    "title": "2024年普通高校招生考生成绩分段统计表（综合）",
    "url": "https://www.sdzk.cn/",
    "note": "完整官方逐分段一分一段表（普通类一段+二段，覆盖约150~750分），由用户购买并提供。换算器直接逐段查表/插值。数据为山东省教育招生考试院公布的成绩分段统计事实。"
  }
}